anfesibena/__init__.py
anfesibena-1.0.2.dist-info/LICENSE.txt
anfesibena-1.0.2.dist-info/METADATA
anfesibena-1.0.2.dist-info/WHEEL
anfesibena-1.0.2.dist-info/top_level.txt
anfesibena-1.0.2.dist-info/RECORD
