Metadata-Version: 2.1
Name: anfesibena
Version: 1.0.2
Summary: numbers with additative and multiplicative inverses
Author-email: Johannes <johannes-programming@mailfence.com>
License: The MIT License (MIT)
Project-URL: Documentation, https://pypi.org/project/anfesibena
Project-URL: Download, https://pypi.org/project/anfesibena/#files
Project-URL: Source, https://github.com/johannes-programming/anfesibena
Classifier: License :: OSI Approved :: MIT License
Classifier: Programming Language :: Python
Classifier: Programming Language :: Python :: 3
Classifier: Programming Language :: Python :: 3 :: Only
Requires-Python: >=3.10
License-File: LICENSE.txt
